ess/nmx/__init__.py
ess/nmx/mtz_io.py
ess/nmx/nexus.py
ess/nmx/py.typed
ess/nmx/reduction.py
ess/nmx/rotation.py
ess/nmx/scaling.py
ess/nmx/streaming.py
ess/nmx/types.py
ess/nmx/data/__init__.py
ess/nmx/mcstas/__init__.py
ess/nmx/mcstas/load.py
ess/nmx/mcstas/xml.py
essnmx-25.3.0.dist-info/licenses/LICENSE
essnmx-25.3.0.dist-info/METADATA
essnmx-25.3.0.dist-info/WHEEL
essnmx-25.3.0.dist-info/top_level.txt
essnmx-25.3.0.dist-info/RECORD
