Metadata-Version: 2.4
Name: essnmx
Version: 25.3.0
Summary: Data reduction for NMX at the European Spallation Source.
Author: Scipp contributors
License: BSD 3-Clause License
Project-URL: Bug Tracker, https://github.com/scipp/essnmx/issues
Project-URL: Documentation, https://scipp.github.io/essnmx
Project-URL: Source, https://github.com/scipp/essnmx
Classifier: Intended Audience :: Science/Research
Classifier: License :: OSI Approved :: BSD License
Classifier: Natural Language :: English
Classifier: Operating System :: OS Independent
Classifier: Programming Language :: Python :: 3
Classifier: Programming Language :: Python :: 3 :: Only
Classifier: Programming Language :: Python :: 3.10
Classifier: Programming Language :: Python :: 3.11
Classifier: Programming Language :: Python :: 3.12
Classifier: Programming Language :: Python :: 3.13
Classifier: Topic :: Scientific/Engineering
Classifier: Typing :: Typed
Requires-Python: >=3.10
License-File: LICENSE
Requires-Dist: dask
Requires-Dist: essreduce>=24.03.0
Requires-Dist: graphviz
Requires-Dist: plopp
Requires-Dist: sciline>=24.06.0
Requires-Dist: scipp>=23.8.0
Requires-Dist: scippnexus>=23.12.0
Requires-Dist: pooch
Requires-Dist: pandas
Requires-Dist: gemmi
Requires-Dist: defusedxml
Provides-Extra: test
Requires-Dist: pytest; extra == "test"
Dynamic: license-file
